[
  {
    "id" : "card0",
    "initialValues" : {
      "opacity" : 1,
      "rotate" : 0,
      "rotateCenter" : 0,
      "scale" : 1,
      "translate" : [
        0,
        0
      ]
    },
    "invokeType" : "auto",
    "keyframes" : [
      {
        "duration" : 0,
        "id" : "240A9531-2805-4D27-987B-E41FB0774BA7",
        "values" : {
          "opacity" : 1,
          "rotate" : 0,
          "rotateCenter" : 0,
          "scale" : 1,
          "translate" : [
            -0.7422417534722222,
            -0.0007244302653360252
          ]
        }
      },
      {
        "duration" : 3,
        "id" : "CBD1A005-C7F4-437E-B35D-56FD0AA47988",
        "values" : {
          "opacity" : 1,
          "rotate" : 0,
          "rotateCenter" : 0,
          "scale" : 1,
          "translate" : [
            0.0027126736111111236,
            -0.009516726011994003
          ]
        }
      },
      {
        "duration" : -3,
        "id" : "20AF8525-2A74-4A69-BAFC-45767703B4C0",
        "values" : {
          "opacity" : 1,
          "rotate" : 0,
          "rotateCenter" : 0,
          "scale" : 1,
          "translate" : [
            0.7923719618055555,
            0.019163086913574406
          ]
        }
      },
      {
        "duration" : 3,
        "id" : "D0D7D448-6A59-4B63-AFA7-982B85E7DB07",
        "values" : {
          "opacity" : 1,
          "rotate" : 0,
          "rotateCenter" : 0,
          "scale" : 1,
          "translate" : [
            0.009060329861111162,
            0.016852535646239324
          ]
        }
      }
    ]
  },
  {
    "id" : "card1",
    "initialValues" : {
      "opacity" : 1,
      "rotate" : 0,
      "rotateCenter" : 0,
      "scale" : 1,
      "translate" : [
        0,
        0
      ]
    },
    "invokeType" : "auto",
    "keyframes" : [
      {
        "duration" : 0,
        "id" : "6E98CDDA-3F87-4F5F-82A8-520D78767B70",
        "values" : {
          "opacity" : 1,
          "rotate" : 0,
          "rotateCenter" : 0,
          "scale" : 1,
          "translate" : [
            0.7923719618055555,
            0.019163086913574406
          ]
        }
      },
      {
        "duration" : 3,
        "id" : "24303E07-AC5A-44A7-A735-B1F55E21DC47",
        "values" : {
          "opacity" : 1,
          "rotate" : 0,
          "rotateCenter" : 0,
          "scale" : 1,
          "translate" : [
            0.009060329861111162,
            0.016852535646239324
          ]
        }
      }
    ]
  }
]
